shopstyle_api/__init__.py
shopstyle_api/api.py
shopstyle_api/exceptions.py
shopstyle_api/tests.py
shopstyle_api/tests/__init__.py
shopstyle_api/tests/tests.py
shopstyle_api-0.0.7.dist-info/LICENSE
shopstyle_api-0.0.7.dist-info/METADATA
shopstyle_api-0.0.7.dist-info/WHEEL
shopstyle_api-0.0.7.dist-info/top_level.txt
shopstyle_api-0.0.7.dist-info/RECORD
